libtrust/__init__.py
libtrust/exceptions.py
libtrust/jsonsign.py
libtrust/keys/__init__.py
libtrust/keys/ec_key.py
libtrust/keys/protocol.py
libtrust/keys/rs_key.py
libtrust/keys/utils.py
libtrust/utils.py
py_libtrust-2.1.1.dist-info/LICENSE
py_libtrust-2.1.1.dist-info/METADATA
py_libtrust-2.1.1.dist-info/WHEEL
py_libtrust-2.1.1.dist-info/RECORD
