Metadata-Version: 2.1
Name: py-libtrust
Version: 2.1.1
Summary: Yet another docker/libtrust implement by python.
Home-page: https://github.com/shabbywu/py-libtrust
License: Apache-2.0
Author: shabbywu
Author-email: shabbywu@qq.com
Requires-Python: >=3.8
Classifier: License :: OSI Approved :: Apache Software License
Classifier: Programming Language :: Python :: 3
Classifier: Programming Language :: Python :: 3.8
Classifier: Programming Language :: Python :: 3.9
Classifier: Programming Language :: Python :: 3.10
Classifier: Programming Language :: Python :: 3.11
Classifier: Programming Language :: Python :: 3.12
Requires-Dist: cryptography (>=37)
Requires-Dist: typing-extensions (>=3.6.5)
Project-URL: Repository, https://github.com/shabbywu/py-libtrust
